LICENSE
MANIFEST.in
README.md
package.json
setup.py
dash_sylvereye/SylvereyeRoadNetwork.py
dash_sylvereye/__init__.py
dash_sylvereye/_imports_.py
dash_sylvereye/dash_sylvereye.min.js
dash_sylvereye/dash_sylvereye.min.js.map
dash_sylvereye/defaults.py
dash_sylvereye/enums.py
dash_sylvereye/metadata.json
dash_sylvereye/package-info.json
dash_sylvereye/utils.py
dash_sylvereye.egg-info/PKG-INFO
dash_sylvereye.egg-info/SOURCES.txt
dash_sylvereye.egg-info/dependency_links.txt
dash_sylvereye.egg-info/requires.txt
dash_sylvereye.egg-info/top_level.txt