Metadata-Version: 1.1
Name: dash-sylvereye
Version: 0.3.0
Summary: Dash Sylvereye is a Plotly Dash component library for producing interactive web-based visualizations of large primal road networks in Python.
Home-page: UNKNOWN
Author: Alberto Garcia-Robledo <alberto.garob@gmail.com>
Author-email: UNKNOWN
License: MIT
Platform: UNKNOWN
Classifier: Framework :: Dash
